odoo10_addon_web_widget_timepicker-10.0.1.0.0-py2.7-nspkg.pth
odoo/addons/web_widget_timepicker/README.rst
odoo/addons/web_widget_timepicker/__init__.py
odoo/addons/web_widget_timepicker/__manifest__.py
odoo/addons/web_widget_timepicker/images/form_view.png
odoo/addons/web_widget_timepicker/images/picker.png
odoo/addons/web_widget_timepicker/static/description/icon.png
odoo/addons/web_widget_timepicker/static/src/css/web_widget_timepicker.css
odoo/addons/web_widget_timepicker/static/src/js/web_widget_timepicker.js
odoo/addons/web_widget_timepicker/static/src/lib/jquery.timepicker/jquery.timepicker.css
odoo/addons/web_widget_timepicker/static/src/lib/jquery.timepicker/jquery.timepicker.js
odoo/addons/web_widget_timepicker/static/src/xml/web_widget_timepicker.xml
odoo/addons/web_widget_timepicker/views/web_widget_timepicker_assets.xml
odoo10_addon_web_widget_timepicker-10.0.1.0.0.dist-info/DESCRIPTION.rst
odoo10_addon_web_widget_timepicker-10.0.1.0.0.dist-info/METADATA
odoo10_addon_web_widget_timepicker-10.0.1.0.0.dist-info/RECORD
odoo10_addon_web_widget_timepicker-10.0.1.0.0.dist-info/WHEEL
odoo10_addon_web_widget_timepicker-10.0.1.0.0.dist-info/metadata.json
odoo10_addon_web_widget_timepicker-10.0.1.0.0.dist-info/namespace_packages.txt
odoo10_addon_web_widget_timepicker-10.0.1.0.0.dist-info/top_level.txt
