Metadata-Version: 2.0
Name: odoo10-addon-web-widget-timepicker
Version: 10.0.1.0.0
Summary: Web Timepicker Widget
Home-page: http://www.vividlab.de
Author: VividLab, Odoo Community Association (OCA), Kaushal Prajapati
Author-email: support@odoo-community.org
License: AGPL-3
Platform: UNKNOWN
Classifier: Programming Language :: Python :: 2.7
Classifier: Framework :: Odoo
Classifier: License :: OSI Approved :: GNU Affero General Public License v3
Requires-Dist: odoo (<10.1dev,>=10.0)
